lymask/__init__.py
lymask/command_line.py
lymask/dataprep_steps.py
lymask/drc_steps.py
lymask/invocation.py
lymask/library.py
lymask/menu.py
lymask/utilities.py
lymask/lymacros/lymask_startup.lym
lymask/lymacros/reload_layers.lym
lymask-0.1.11.dist-info/LICENSE
lymask-0.1.11.dist-info/METADATA
lymask-0.1.11.dist-info/WHEEL
lymask-0.1.11.dist-info/entry_points.txt
lymask-0.1.11.dist-info/top_level.txt
lymask-0.1.11.dist-info/RECORD
