Metadata-Version: 2.1
Name: lymask
Version: 0.1.11
Summary: Mask dataprep with klayout
Home-page: https://github.com/atait/lymask/
Author: Alex Tait, Adam McCaughan, Sonia Buckley, Jeff Chiles, Jeff Shainline, Rich Mirin, Sae Woo Nam
Author-email: alexander.tait@nist.gov
License: MIT
License-File: LICENSE
Requires-Dist: klayout
Requires-Dist: lygadgets
Requires-Dist: PyYAML
